{"story5":"实际上的保罗·班扬传说，并没有在当时的开拓时代里流传过。 一般现在所熟知的那些天马行空的巨人传说部分， 都是进入20世纪之后被捏造出来的。 班扬这种民间传说的英雄，只不过是空有其名的浅薄虚假之物， 这也许就是作为『Servant』的她，无法很好地发挥出传说中的力量的原因。","detail":"美国开拓时代Tall·Tale（奇闻怪事）中登场的樵夫。 据描述，她实际为高耸入云的巨大男人。 从她的巨大中诞生的超大规模的传说有很多个，北美大部分的特殊地理坏境，据说也是受了班扬行动的影响。 其被作为幼女召唤的原因未知。","story3":"班扬爱着人们，一边相信着只有文明的发展才能让人们幸福，一边开拓未开荒的土地。 为了能让大家过上富裕的生活， 就算是面对伟大的大自然也会不留有一丝顾虑的破坏。 而这种行为对未来的人类来说会带来怎样的影响， 幼小的班扬仍然无法理解。","id":"174","story1":"身高／体重：不确定 出典：传说 地域：美国、加拿大 属性：中立·中庸 性别：女性 通常的身高，目测来看可确定有3米以上，然而正确的数值 每次都会发生变化因此无法完全确定。","story4":"『惊人的伟业』 等级：Ａ 种类：对军宝具 Marvelous Exploits 将美国本身化为概念宝具， 并将建国史能量化，猛击敌人并砍倒敌人所在之地的一切…… 虽然其本人是这么描述的，但实际上怎么看，都只是用巨大的脚把敌人踩扁。 也是所有宝具中，速度快的惊人的一个。","story2":"就如传说那样，她将巨大的蓝色公牛作为伙伴带在身边， 但那种形状，不论怎么看都是和牛不沾边的球体妖怪。 或许那可能是在美国开拓时代里所流传的Fearsome·Critters， 以现在的来说就是“UMA（未确认生物体）”之类的玩意吧。","story6":"即便保罗·班扬的传说是虚假的 但她那些愉快的故事，至今传颂了100年之久，直到现在也广为人知。 不管有什么样的经历 不管是怎样让人发笑的荒谬 传说这种东西，正是被世人所爱，所代代传颂的东西。 愿这份情感，也能传递到她身边。"}