{
    "story5": "宝具『力屠祝福之剑』 等级：Ｂ 种类：对人宝具 让持有主远离一切恶意和害意的圣剑。从任何敌人手中守护持有者，从这个意义上来说的确是可夸耀无敌的圣剑。",
    "detail": "圣乔治（Georgius），又叫圣乔治（George）。以持圣剑阿斯卡隆退治了巨龙的逸话而出名。骑乘着只有一次能够使对手的攻击无效化的爱马贝亚德（Bayard）。",
    "story3": "殉教者之魂：Ｂ＋ 将精神面的干涉无效化。接受过拷问等各种各样的手段，逼迫他抛弃宗教，却不曾为此屈服的圣乔治，是拥有极其坚韧的信仰之人。",
    "id": "24",
    "story1": "身高／体重：180cm·95kg 出典：《黄金传说》《圣乔治传说》 地域：欧洲 属性：秩序·善　　性別：男性 在守势中发挥力量的英灵。",
    "story4": "作为圣人，圣乔治的武勇传说，与普通的骑士不相上下。在经过以献祭平息毒龙之怒的街道时，圣乔治掷枪将龙退治。有一种说法说他是魔女养育长大的。",
    "story2": "守护骑士：Ａ＋ 守护他人的时候，让防御力暂时上升。圣乔治身为众多国家和地域的守护者，经常受到祈求守护的期待。而那些期待，给予了他无限的守护之力。",
    "story6": "圣乔治为了拯救世界，一定会高兴地奉献自己的灵魂的吧。他会好不踌躇地一直牵挂你的性命。如果你希望报答他的献身，就采取作为Master应该采取的正确行动。"
}