{"story5":"作为人造人出生，一切都如同疾风经过一般，她的寿命非常短暂。因此，也许她非常希望得到认可吧，从她那为之奉献一生的父亲那里。然而，莫德雷德也同样没能做到去揣度亚瑟的苦恼。","detail":"莫德雷德身为圆桌骑士之一，是亚瑟王的嫡子。同时也为传说画上了休止符——在卡姆兰之丘，作为叛逆骑士，给予亚瑟王最后一击。","story3":"由于莫德雷德是人造人，其成长速度极快，出生后数年便已作为骑士侍奉亚瑟王了。另外，由于其在能力上仿制了亚瑟王，不久她就作为骑士崭露头角。","id":"76","story1":"身高／体重：154cm·42kg 出典：亚瑟王传说 地域：英国 属性：混沌·中庸 性别：女性 与阿尔托莉雅体型完全一样。","story4":"与摩根的意愿相悖，莫德雷德憧憬父亲，希望被父亲认可，然而这随着亚瑟王的拒绝发生了转变。为了践踏父亲的伟业，她开始“研磨毒牙”。原本形势已然达到极限的不列颠，随着这两人的激烈冲突而崩坏了。","story2":"莫德雷德是由既是亚瑟王的姐姐，又是其宿敌的魔女摩根的奸计而生出的人工生命——人造人（Homunculus）的一种。 为了讨伐亚瑟，并成为超越亚瑟的王，莫德雷德诞生了。","story6":"对待莫德雷德的方法很简单。不说亚瑟王的坏话；不称赞亚瑟王；不要把她作为女性对待；也不要露骨地把她当做男性对待；不要过于死板严格；不为其他Servant神魂颠倒；认真听取她的意见。简单吧？"}