{
    "id": "812",
    "name": "传说与事实",
    "illustrator": "未知画师",
    "rarity": 4,
    "cost": 9,
    "minAndMaxHP": "100",
    "minAndMaxATK": "100",
    "effect": "拿破仑(Archer)装备，且自身在场时，己方全体的Buster指令卡性能提升10%＆宝具威力提升10%",
    "effectImg": "红放",
    "lore": "根据传说，\n拿破仑的字典里没有不可能这几个字。\n\n根据记录，\n拿破仑喜欢西班牙的雪茄。\n\n他不否定。\n在外形方面，他或许会半开玩笑地糊弄过去，\n但事关传说、轶事、记录方面，他不会否定。\n他总会笑着说，\n「至少对现在的我来说算是事实吧」。\n\n当然，在除他以外的英灵的身上，\n也时常伴随着传说与事实的相关或相克。\n既然如此，那么拿破仑的固有特异性又是什么？\n\n——是接受一切的言行。\n——无论是传说、轶事、还是记录。",
    "bondServantID": "212"
}

